cv2/__init__.py
cv2/load_config_py2.py
cv2/load_config_py3.py
opencv_neuro-4.6.0.dist-info/METADATA
opencv_neuro-4.6.0.dist-info/WHEEL
opencv_neuro-4.6.0.dist-info/top_level.txt
opencv_neuro-4.6.0.dist-info/RECORD
